cytomat/__init__.py
cytomat/barcode_scanner.py
cytomat/climate_controller.py
cytomat/cytomat.py
cytomat/errors.py
cytomat/maintenance_controller.py
cytomat/plate_handler.py
cytomat/serial_port.py
cytomat/shaker_controller.py
cytomat/status.py
cytomat/swap_station.py
cytomat/tests/basic_tests.py
cytomat/tests/test_comm.py
cytomat/tests/test_status.py
cytomat/utils.py
open_cytomat-0.1.2.dist-info/LICENSE
open_cytomat-0.1.2.dist-info/METADATA
open_cytomat-0.1.2.dist-info/WHEEL
open_cytomat-0.1.2.dist-info/RECORD
